[
    {
        "name": "silence final",
        "author": "Unknown",
        "transcribedBy": "Unknown",
        "isComposed": true,
        "bpm": 430,
        "bitsPerPage": 16,
        "pitchLevel": 9,
        "isEncrypted": false,
        "songNotes": [
            {
                "time": 0,
                "key": "1Key5"
            },
            {
                "time": 556,
                "key": "1Key7"
            },
            {
                "time": 1112,
                "key": "1Key3"
            },
            {
                "time": 1112,
                "key": "1Key5"
            },
            {
                "time": 1112,
                "key": "1Key7"
            },
            {
                "time": 1112,
                "key": "1Key9"
            },
            {
                "time": 2224,
                "key": "1Key8"
            },
            {
                "time": 2224,
                "key": "1Key11"
            },
            {
                "time": 3336,
                "key": "1Key4"
            },
            {
                "time": 3336,
                "key": "1Key6"
            },
            {
                "time": 4448,
                "key": "1Key1"
            },
            {
                "time": 4448,
                "key": "1Key6"
            },
            {
                "time": 5004,
                "key": "1Key5"
            },
            {
                "time": 5004,
                "key": "1Key7"
            },
            {
                "time": 5560,
                "key": "1Key2"
            },
            {
                "time": 5560,
                "key": "1Key5"
            },
            {
                "time": 5560,
                "key": "1Key8"
            },
            {
                "time": 6672,
                "key": "1Key5"
            },
            {
                "time": 6672,
                "key": "1Key7"
            },
            {
                "time": 6672,
                "key": "1Key11"
            },
            {
                "time": 7784,
                "key": "1Key5"
            },
            {
                "time": 8896,
                "key": "1Key2"
            },
            {
                "time": 8896,
                "key": "1Key5"
            },
            {
                "time": 9452,
                "key": "1Key5"
            },
            {
                "time": 9452,
                "key": "1Key7"
            },
            {
                "time": 10008,
                "key": "1Key0"
            },
            {
                "time": 10008,
                "key": "1Key3"
            },
            {
                "time": 10008,
                "key": "1Key5"
            },
            {
                "time": 10008,
                "key": "1Key8"
            },
            {
                "time": 11120,
                "key": "1Key8"
            },
            {
                "time": 11120,
                "key": "1Key11"
            },
            {
                "time": 12232,
                "key": "1Key4"
            },
            {
                "time": 12232,
                "key": "1Key6"
            },
            {
                "time": 12788,
                "key": "1Key9"
            },
            {
                "time": 13344,
                "key": "1Key1"
            },
            {
                "time": 13344,
                "key": "1Key6"
            },
            {
                "time": 13900,
                "key": "1Key5"
            },
            {
                "time": 13900,
                "key": "1Key7"
            },
            {
                "time": 14456,
                "key": "1Key2"
            },
            {
                "time": 14456,
                "key": "1Key4"
            },
            {
                "time": 14456,
                "key": "1Key5"
            },
            {
                "time": 14456,
                "key": "1Key8"
            },
            {
                "time": 15568,
                "key": "1Key5"
            },
            {
                "time": 15568,
                "key": "1Key7"
            },
            {
                "time": 15568,
                "key": "1Key14"
            },
            {
                "time": 16680,
                "key": "1Key11"
            },
            {
                "time": 17792,
                "key": "1Key4"
            },
            {
                "time": 17792,
                "key": "1Key5"
            },
            {
                "time": 18348,
                "key": "1Key7"
            },
            {
                "time": 18904,
                "key": "1Key3"
            },
            {
                "time": 18904,
                "key": "1Key5"
            },
            {
                "time": 18904,
                "key": "1Key9"
            },
            {
                "time": 19460,
                "key": "1Key0"
            },
            {
                "time": 20016,
                "key": "1Key3"
            },
            {
                "time": 20016,
                "key": "1Key5"
            },
            {
                "time": 20572,
                "key": "1Key3"
            },
            {
                "time": 21128,
                "key": "1Key1"
            },
            {
                "time": 21128,
                "key": "1Key4"
            },
            {
                "time": 21684,
                "key": "1Key6"
            },
            {
                "time": 22240,
                "key": "1Key4"
            },
            {
                "time": 22240,
                "key": "1Key6"
            },
            {
                "time": 22796,
                "key": "1Key5"
            },
            {
                "time": 22796,
                "key": "1Key7"
            },
            {
                "time": 23352,
                "key": "1Key2"
            },
            {
                "time": 23352,
                "key": "1Key4"
            },
            {
                "time": 23352,
                "key": "1Key5"
            },
            {
                "time": 23352,
                "key": "1Key8"
            },
            {
                "time": 23908,
                "key": "1Key2"
            },
            {
                "time": 24464,
                "key": "1Key5"
            },
            {
                "time": 24464,
                "key": "1Key7"
            },
            {
                "time": 25020,
                "key": "1Key2"
            },
            {
                "time": 25576,
                "key": "1Key4"
            },
            {
                "time": 26132,
                "key": "1Key1"
            },
            {
                "time": 26688,
                "key": "1Key4"
            },
            {
                "time": 26688,
                "key": "1Key5"
            },
            {
                "time": 27244,
                "key": "1Key1"
            },
            {
                "time": 27244,
                "key": "1Key7"
            },
            {
                "time": 27800,
                "key": "1Key0"
            },
            {
                "time": 27800,
                "key": "1Key3"
            },
            {
                "time": 27800,
                "key": "1Key5"
            },
            {
                "time": 27800,
                "key": "1Key8"
            },
            {
                "time": 28356,
                "key": "1Key0"
            },
            {
                "time": 28912,
                "key": "1Key5"
            },
            {
                "time": 29468,
                "key": "1Key3"
            },
            {
                "time": 30024,
                "key": "1Key1"
            },
            {
                "time": 30024,
                "key": "1Key4"
            },
            {
                "time": 30580,
                "key": "1Key1"
            },
            {
                "time": 30580,
                "key": "1Key9"
            },
            {
                "time": 31136,
                "key": "1Key4"
            },
            {
                "time": 31136,
                "key": "1Key6"
            },
            {
                "time": 31692,
                "key": "1Key1"
            },
            {
                "time": 31692,
                "key": "1Key7"
            },
            {
                "time": 32248,
                "key": "1Key5"
            },
            {
                "time": 32804,
                "key": "1Key2"
            },
            {
                "time": 33360,
                "key": "1Key7"
            },
            {
                "time": 33916,
                "key": "1Key5"
            },
            {
                "time": 34472,
                "key": "1Key9"
            },
            {
                "time": 37808,
                "key": "1Key5"
            },
            {
                "time": 38364,
                "key": "1Key9"
            },
            {
                "time": 38920,
                "key": "1Key3"
            },
            {
                "time": 38920,
                "key": "1Key5"
            },
            {
                "time": 38920,
                "key": "1Key7"
            },
            {
                "time": 38920,
                "key": "1Key9"
            },
            {
                "time": 40588,
                "key": "1Key9"
            },
            {
                "time": 40866,
                "key": "1Key6"
            },
            {
                "time": 41144,
                "key": "1Key1"
            },
            {
                "time": 41144,
                "key": "1Key4"
            },
            {
                "time": 41144,
                "key": "1Key6"
            },
            {
                "time": 42812,
                "key": "1Key5"
            },
            {
                "time": 43090,
                "key": "1Key7"
            },
            {
                "time": 43368,
                "key": "1Key2"
            },
            {
                "time": 43368,
                "key": "1Key4"
            },
            {
                "time": 43368,
                "key": "1Key5"
            },
            {
                "time": 46704,
                "key": "1Key5"
            },
            {
                "time": 47260,
                "key": "1Key9"
            },
            {
                "time": 47816,
                "key": "1Key3"
            },
            {
                "time": 47816,
                "key": "1Key5"
            },
            {
                "time": 47816,
                "key": "1Key7"
            },
            {
                "time": 47816,
                "key": "1Key9"
            },
            {
                "time": 49484,
                "key": "1Key9"
            },
            {
                "time": 49762,
                "key": "1Key13"
            },
            {
                "time": 50040,
                "key": "1Key1"
            },
            {
                "time": 50040,
                "key": "1Key4"
            },
            {
                "time": 50040,
                "key": "1Key6"
            },
            {
                "time": 50040,
                "key": "1Key8"
            },
            {
                "time": 51708,
                "key": "1Key14"
            },
            {
                "time": 51986,
                "key": "1Key11"
            },
            {
                "time": 52264,
                "key": "1Key2"
            },
            {
                "time": 52264,
                "key": "1Key5"
            },
            {
                "time": 52264,
                "key": "1Key7"
            },
            {
                "time": 52820,
                "key": "1Key14"
            },
            {
                "time": 53098,
                "key": "1Key9"
            },
            {
                "time": 53932,
                "key": "1Key7"
            },
            {
                "time": 54210,
                "key": "1Key2"
            },
            {
                "time": 55600,
                "key": "1Key5"
            },
            {
                "time": 56156,
                "key": "1Key9"
            },
            {
                "time": 56712,
                "key": "1Key3"
            },
            {
                "time": 56712,
                "key": "1Key5"
            },
            {
                "time": 56712,
                "key": "1Key7"
            },
            {
                "time": 56712,
                "key": "1Key9"
            },
            {
                "time": 57268,
                "key": "1Key0"
            },
            {
                "time": 57824,
                "key": "1Key5"
            },
            {
                "time": 58380,
                "key": "1Key9"
            },
            {
                "time": 58658,
                "key": "1Key6"
            },
            {
                "time": 58936,
                "key": "1Key1"
            },
            {
                "time": 58936,
                "key": "1Key4"
            },
            {
                "time": 58936,
                "key": "1Key6"
            },
            {
                "time": 59492,
                "key": "1Key1"
            },
            {
                "time": 60048,
                "key": "1Key6"
            },
            {
                "time": 60604,
                "key": "1Key7"
            },
            {
                "time": 60882,
                "key": "1Key4"
            },
            {
                "time": 61160,
                "key": "1Key2"
            },
            {
                "time": 61160,
                "key": "1Key4"
            },
            {
                "time": 61160,
                "key": "1Key5"
            },
            {
                "time": 61716,
                "key": "1Key2"
            },
            {
                "time": 62272,
                "key": "1Key7"
            },
            {
                "time": 62828,
                "key": "1Key2"
            },
            {
                "time": 63384,
                "key": "1Key7"
            },
            {
                "time": 63940,
                "key": "1Key2"
            },
            {
                "time": 64496,
                "key": "1Key4"
            },
            {
                "time": 64496,
                "key": "1Key7"
            },
            {
                "time": 65052,
                "key": "1Key2"
            },
            {
                "time": 65330,
                "key": "1Key4"
            },
            {
                "time": 65608,
                "key": "1Key0"
            },
            {
                "time": 65608,
                "key": "1Key3"
            },
            {
                "time": 65608,
                "key": "1Key5"
            },
            {
                "time": 66164,
                "key": "1Key0"
            },
            {
                "time": 66720,
                "key": "1Key5"
            },
            {
                "time": 67276,
                "key": "1Key3"
            },
            {
                "time": 67832,
                "key": "1Key1"
            },
            {
                "time": 67832,
                "key": "1Key4"
            },
            {
                "time": 67832,
                "key": "1Key6"
            },
            {
                "time": 68388,
                "key": "1Key1"
            },
            {
                "time": 68944,
                "key": "1Key6"
            },
            {
                "time": 68944,
                "key": "1Key8"
            },
            {
                "time": 69500,
                "key": "1Key5"
            },
            {
                "time": 69500,
                "key": "1Key7"
            },
            {
                "time": 69778,
                "key": "1Key6"
            },
            {
                "time": 69778,
                "key": "1Key8"
            },
            {
                "time": 70056,
                "key": "1Key2"
            },
            {
                "time": 70056,
                "key": "1Key5"
            },
            {
                "time": 70056,
                "key": "1Key7"
            },
            {
                "time": 70612,
                "key": "1Key2"
            },
            {
                "time": 71168,
                "key": "1Key5"
            },
            {
                "time": 71724,
                "key": "1Key7"
            },
            {
                "time": 72002,
                "key": "1Key5"
            },
            {
                "time": 72280,
                "key": "1Key2"
            },
            {
                "time": 72280,
                "key": "1Key5"
            }
        ]
    }
]